openmemory_mcp_bridge/__init__.py
openmemory_mcp_bridge/cli.py
openmemory_mcp_bridge/main.py
openmemory_mcp_bridge-0.3.2.dist-info/METADATA
openmemory_mcp_bridge-0.3.2.dist-info/WHEEL
openmemory_mcp_bridge-0.3.2.dist-info/entry_points.txt
openmemory_mcp_bridge-0.3.2.dist-info/RECORD
