Metadata-Version: 2.4
Name: openmemory-mcp-bridge
Version: 0.3.2
Summary: MCP bridge for OpenMemory SSE endpoints
Project-URL: Homepage, https://github.com/TensorBlast/mem0
Project-URL: Repository, https://github.com/TensorBlast/mem0
Project-URL: Bug Tracker, https://github.com/TensorBlast/mem0/issues
Author: Ankit Pasi
License: MIT
Classifier: Development Status :: 4 - Beta
Classifier: Intended Audience :: Developers
Classifier: License :: OSI Approved :: MIT License
Classifier: Programming Language :: Python :: 3
Classifier: Programming Language :: Python :: 3.8
Classifier: Programming Language :: Python :: 3.9
Classifier: Programming Language :: Python :: 3.10
Classifier: Programming Language :: Python :: 3.11
Classifier: Programming Language :: Python :: 3.12
Requires-Python: >=3.8
Requires-Dist: click>=8.0.0
Requires-Dist: httpx>=0.24.0
